{"cameraMode":{"drawMode":0,"name":"Shaded","section":"Shading Mode"},"sceneLighting":true,"audioPlay":false,"sceneViewState":{"showFog":true,"showMaterialUpdate":false,"showSkybox":true,"showFlares":true,"showImageEffects":true,"showParticleSystems":true},"in2DMode":false,"pivot":{"x":-67.49964141845703,"y":0.7613383531570435,"z":0.9453394412994385},"rotation":{"x":-0.1625807285308838,"y":-0.715542197227478,"z":0.17738403379917146,"w":-0.6558392643928528},"size":6.0422186851501469,"orthographic":false}